{
  "date": "2026-01-28",
  "games": [
    {
      "game_id": "LAL_CLE_20260128",
      "home": "CLE",
      "away": "LAL",
      "time": "7:00 PM ET",
      "home_score": {
        "floor": 90.80000000000001,
        "ev": 99.77666666666667,
        "ceiling": 109.0
      },
      "away_score": {
        "floor": 88.0,
        "ev": 97.11333333333333,
        "ceiling": 106.0
      },
      "blowout_pct": 0.28
    },
    {
      "game_id": "CHI_IND_20260128",
      "home": "IND",
      "away": "CHI",
      "time": "7:00 PM ET",
      "home_score": {
        "floor": 85.0,
        "ev": 93.67666666666666,
        "ceiling": 102.0
      },
      "away_score": {
        "floor": 86.0,
        "ev": 94.18666666666667,
        "ceiling": 103.0
      },
      "blowout_pct": 0.21333333333333335
    },
    {
      "game_id": "ATL_BOS_20260128",
      "home": "BOS",
      "away": "ATL",
      "time": "7:30 PM ET",
      "home_score": {
        "floor": 87.0,
        "ev": 96.25,
        "ceiling": 105.0
      },
      "away_score": {
        "floor": 87.0,
        "ev": 96.21333333333334,
        "ceiling": 105.0
      },
      "blowout_pct": 0.24666666666666667
    },
    {
      "game_id": "ORL_MIA_20260128",
      "home": "MIA",
      "away": "ORL",
      "time": "7:30 PM ET",
      "home_score": {
        "floor": 83.0,
        "ev": 92.27,
        "ceiling": 102.0
      },
      "away_score": {
        "floor": 84.0,
        "ev": 93.69666666666667,
        "ceiling": 103.0
      },
      "blowout_pct": 0.24666666666666667
    },
    {
      "game_id": "NYK_TOR_20260128",
      "home": "TOR",
      "away": "NYK",
      "time": "7:30 PM ET",
      "home_score": {
        "floor": 86.0,
        "ev": 96.37333333333333,
        "ceiling": 105.20000000000002
      },
      "away_score": {
        "floor": 86.0,
        "ev": 95.53333333333333,
        "ceiling": 105.0
      },
      "blowout_pct": 0.26666666666666666
    },
    {
      "game_id": "CHA_MEM_20260128",
      "home": "MEM",
      "away": "CHA",
      "time": "8:00 PM ET",
      "home_score": {
        "floor": 83.0,
        "ev": 93.15333333333334,
        "ceiling": 103.0
      },
      "away_score": {
        "floor": 85.0,
        "ev": 94.16,
        "ceiling": 103.0
      },
      "blowout_pct": 0.2633333333333333
    },
    {
      "game_id": "MIN_DAL_20260128",
      "home": "DAL",
      "away": "MIN",
      "time": "8:30 PM ET",
      "home_score": {
        "floor": 89.0,
        "ev": 98.96,
        "ceiling": 108.0
      },
      "away_score": {
        "floor": 89.80000000000001,
        "ev": 98.38,
        "ceiling": 108.0
      },
      "blowout_pct": 0.2866666666666667
    },
    {
      "game_id": "GSW_UTA_20260128",
      "home": "UTA",
      "away": "GSW",
      "time": "9:00 PM ET",
      "home_score": {
        "floor": 86.0,
        "ev": 95.57,
        "ceiling": 104.0
      },
      "away_score": {
        "floor": 88.0,
        "ev": 97.58,
        "ceiling": 108.0
      },
      "blowout_pct": 0.30666666666666664
    },
    {
      "game_id": "SAS_HOU_20260128",
      "home": "HOU",
      "away": "SAS",
      "time": "9:30 PM ET",
      "home_score": {
        "floor": 83.0,
        "ev": 92.44666666666667,
        "ceiling": 101.20000000000002
      },
      "away_score": {
        "floor": 83.0,
        "ev": 93.3,
        "ceiling": 103.0
      },
      "blowout_pct": 0.25666666666666665
    }
  ]
}